rancrypt/RCrypt.py
rancrypt/__init__.py
rcrypt-0.0.1.dist-info/LICENSE
rcrypt-0.0.1.dist-info/METADATA
rcrypt-0.0.1.dist-info/WHEEL
rcrypt-0.0.1.dist-info/top_level.txt
rcrypt-0.0.1.dist-info/RECORD
