Metadata-Version: 2.1
Name: rcrypt
Version: 0.0.1
Summary: Libraries for encryption and alignment
Home-page: 
Author: ranyu
Author-email: wy176404@163.com
Classifier: Programming Language :: Python :: 3.8
Classifier: License :: OSI Approved :: MIT License
Classifier: Operating System :: OS Independent
License-File: LICENSE
Requires-Dist: bcrypt ~=4.1.3
